pyloco_task_echo/__init__.py
pyloco_task_echo/echo.py
pyloco_task_echo-0.0.3.dist-info/METADATA
pyloco_task_echo-0.0.3.dist-info/WHEEL
pyloco_task_echo-0.0.3.dist-info/entry_points.txt
pyloco_task_echo-0.0.3.dist-info/top_level.txt
pyloco_task_echo-0.0.3.dist-info/RECORD
